{
  "key": "636EEW8Q",
  "item_type": "journalArticle",
  "publication_year": "2024",
  "author": "Baresi, Luciano; Quattrocchi, Giovanni; Rasi, Nicholas",
  "title": "A qualitative and quantitative analysis of container engines",
  "publication_title": "Journal of Systems and Software",
  "isbn": "",
  "issn": "0164-1212",
  "doi": "10.1016/j.jss.2024.111965",
  "url": "https://www.sciencedirect.com/science/article/pii/S0164121224000086",
  "abstract_note": "Containerization is a virtualization technique that allows one to create and run executables consistently on any infrastructure. Compared to virtual machines, containers are lighter since they do not bundle a (guest) operating system but they share its kernel, and they only include the files, libraries, and dependencies that are required to properly execute a process. In the past few years, multiple container engines (i.e., tools for configuring, executing, and managing containers) have been developed ranging from some that are “general purpose”, and mostly employed for Cloud executions, to others that are built for specific contexts, namely Internet of Things and High-Performance Computing. Given the importance of this technology for many practitioners and researchers, this paper analyzes six state-of-the-art container engines and compares them through a comprehensive study of their characteristics and performance. The results are organized around 0 findings that aim to help the readers understand the differences among the technologies and help them choose the best approach for their needs. Editor’s note: Open Science material was validated by the Journal of Systems and Software Open Science Board.",
  "date": "2024-04-01",
  "date_added": "2026-03-08 11:53:22",
  "date_modified": "2026-03-08 11:53:22",
  "access_date": "2026-03-08 11:53:22",
  "pages": "111965",
  "num_pages": "",
  "issue": "",
  "volume": "210",
  "number_of_volumes": "",
  "journal_abbreviation": "Journal of Systems and Software",
  "short_title": "",
  "series": "",
  "series_number": "",
  "series_text": "",
  "series_title": "",
  "publisher": "",
  "place": "",
  "language": "",
  "rights": "",
  "type": "",
  "archive": "",
  "archive_location": "",
  "library_catalog": "ScienceDirect",
  "call_number": "",
  "extra": "",
  "notes": "",
  "file_attachments": "/Users/szymon/Zotero/storage/LE4QULEP/S0164121224000086.html; /Users/szymon/Zotero/storage/ZVVG25Q2/Baresi et al. - 2024 - A qualitative and quantitative analysis of container engines.pdf",
  "link_attachments": "",
  "manual_tags": "",
  "automatic_tags": "Cloud computing; Container engines; Containerization; High-performance computing; Internet of things; Performance",
  "editor": "",
  "series_editor": "",
  "translator": "",
  "contributor": "",
  "attorney_agent": "",
  "book_author": "",
  "cast_member": "",
  "commenter": "",
  "composer": "",
  "cosponsor": "",
  "counsel": "",
  "interviewer": "",
  "producer": "",
  "recipient": "",
  "reviewed_author": "",
  "scriptwriter": "",
  "words_by": "",
  "guest": "",
  "number": "",
  "edition": "",
  "running_time": "",
  "scale": "",
  "medium": "",
  "artwork_size": "",
  "filing_date": "",
  "application_number": "",
  "assignee": "",
  "issuing_authority": "",
  "country": "",
  "meeting_name": "",
  "conference_name": "",
  "court": "",
  "references": "",
  "reporter": "",
  "legal_status": "",
  "priority_numbers": "",
  "programming_language": "",
  "version": "",
  "system": "",
  "code": "",
  "code_number": "",
  "section": "",
  "session": "",
  "committee": "",
  "history": "",
  "legislative_body": ""
}