{
  "key": "8SG9DDDD",
  "item_type": "journalArticle",
  "publication_year": "2025",
  "author": "Mårtensson, Torvald",
  "title": "So much more than test cases – An industrial study on testing of software units and components",
  "publication_title": "Journal of Systems and Software",
  "isbn": "",
  "issn": "0164-1212",
  "doi": "10.1016/j.jss.2025.112479",
  "url": "https://www.sciencedirect.com/science/article/pii/S0164121225001475",
  "abstract_note": "While software-developing organizations increasingly write test cases and continuously run them to find defects and ensure quality, the associated maintenance and execution costs increase over time. According to practitioners in the software industry, more test cases is not the solution, which calls for other methods and tools that can complement traditional test cases. Based on a cross-company workshop with 30 participants, three focus groups with 19 participants, and a validation workshop with 30 participants, this paper presents insights from practitioners at six large-scale companies, describing experiences from real industrial settings with regards to testing of software units and components. As every tool is also a cost for the organization, this paper presents a structured and holistic approach based on grounded theory, where methods and tools are evaluated and selected from four categories, representing test activities with different purposes: Optimize feedback loops, Improve test efficiency, Improve test suite effectiveness, and Technical debt management. The participants in the study also described how methods and tools used within their companies were often not well described in the company’s ways-of-working, which caused frustration and confusion. Feedback from the continuous integration and delivery pipeline must be understandable (describing what the problem is), actionable (describing what the developer needs to do), and explained (describing and motivating why this is important). The findings from this study provide actionable strategies for how testing of units and components can be conducted in a more structured way, which could help companies cut costs, save time and identify problems earlier.",
  "date": "2025-10-01",
  "date_added": "2026-03-08 11:02:15",
  "date_modified": "2026-03-08 11:02:15",
  "access_date": "2026-03-08 11:02:15",
  "pages": "112479",
  "num_pages": "",
  "issue": "",
  "volume": "228",
  "number_of_volumes": "",
  "journal_abbreviation": "Journal of Systems and Software",
  "short_title": "",
  "series": "",
  "series_number": "",
  "series_text": "",
  "series_title": "",
  "publisher": "",
  "place": "",
  "language": "",
  "rights": "",
  "type": "",
  "archive": "",
  "archive_location": "",
  "library_catalog": "ScienceDirect",
  "call_number": "",
  "extra": "",
  "notes": "",
  "file_attachments": "/Users/szymon/Zotero/storage/492HG8DP/Mårtensson - 2025 - So much more than test cases – An industrial study on testing of software units and components.pdf; /Users/szymon/Zotero/storage/Q6PTW8VX/S0164121225001475.html",
  "link_attachments": "",
  "manual_tags": "",
  "automatic_tags": "In practice; Industrial study; Software component; Software testing; Software unit; Test methods; Test tools",
  "editor": "",
  "series_editor": "",
  "translator": "",
  "contributor": "",
  "attorney_agent": "",
  "book_author": "",
  "cast_member": "",
  "commenter": "",
  "composer": "",
  "cosponsor": "",
  "counsel": "",
  "interviewer": "",
  "producer": "",
  "recipient": "",
  "reviewed_author": "",
  "scriptwriter": "",
  "words_by": "",
  "guest": "",
  "number": "",
  "edition": "",
  "running_time": "",
  "scale": "",
  "medium": "",
  "artwork_size": "",
  "filing_date": "",
  "application_number": "",
  "assignee": "",
  "issuing_authority": "",
  "country": "",
  "meeting_name": "",
  "conference_name": "",
  "court": "",
  "references": "",
  "reporter": "",
  "legal_status": "",
  "priority_numbers": "",
  "programming_language": "",
  "version": "",
  "system": "",
  "code": "",
  "code_number": "",
  "section": "",
  "session": "",
  "committee": "",
  "history": "",
  "legislative_body": ""
}