{
  "key": "U6QNMIYG",
  "item_type": "journalArticle",
  "publication_year": "2022",
  "author": "Asokan, Deepak Ram; Huq, Fahian Anisul; Smith, Christopher M.; Stevenson, Mark",
  "title": "Socially responsible operations in the Industry 4.0 era: post-COVID-19 technology adoption and perspectives on future research",
  "publication_title": "International Journal of Operations & Production Management",
  "isbn": "",
  "issn": "0144-3577",
  "doi": "10.1108/IJOPM-01-2022-0069",
  "url": "http://www.emerald.com/ijopm/article/42/13/185-217/389976",
  "abstract_note": "Purpose – As focal firms in supply networks reflect on their experiences of the pandemic and begin to rethink their operations and supply chains, there is a significant opportunity to leverage digital technological advances to enhance socially responsible operations performance (SROP). This paper develops a novel framework for exploring the adoption of Industry 4.0 technologies for improving SROP. It highlights current best-practice examples and presents future research pathways.",
  "date": "2022-12-19",
  "date_added": "2026-03-03 21:50:03",
  "date_modified": "2026-03-03 21:50:03",
  "access_date": "2026-03-03 21:50:03",
  "pages": "185-217",
  "num_pages": "",
  "issue": "13",
  "volume": "42",
  "number_of_volumes": "",
  "journal_abbreviation": "IJOPM",
  "short_title": "Socially responsible operations in the Industry 4.0 era",
  "series": "",
  "series_number": "",
  "series_text": "",
  "series_title": "",
  "publisher": "",
  "place": "",
  "language": "en",
  "rights": "https://www.emerald.com/insight/site-policies",
  "type": "",
  "archive": "",
  "archive_location": "",
  "library_catalog": "DOI.org (Crossref)",
  "call_number": "",
  "extra": "",
  "notes": "",
  "file_attachments": "/Users/szymon/Zotero/storage/KPEINVSX/Asokan et al. - 2022 - Socially responsible operations in the Industry 4.0 era post-COVID-19 technology adoption and persp.pdf",
  "link_attachments": "",
  "manual_tags": "",
  "automatic_tags": "",
  "editor": "",
  "series_editor": "",
  "translator": "",
  "contributor": "",
  "attorney_agent": "",
  "book_author": "",
  "cast_member": "",
  "commenter": "",
  "composer": "",
  "cosponsor": "",
  "counsel": "",
  "interviewer": "",
  "producer": "",
  "recipient": "",
  "reviewed_author": "",
  "scriptwriter": "",
  "words_by": "",
  "guest": "",
  "number": "",
  "edition": "",
  "running_time": "",
  "scale": "",
  "medium": "",
  "artwork_size": "",
  "filing_date": "",
  "application_number": "",
  "assignee": "",
  "issuing_authority": "",
  "country": "",
  "meeting_name": "",
  "conference_name": "",
  "court": "",
  "references": "",
  "reporter": "",
  "legal_status": "",
  "priority_numbers": "",
  "programming_language": "",
  "version": "",
  "system": "",
  "code": "",
  "code_number": "",
  "section": "",
  "session": "",
  "committee": "",
  "history": "",
  "legislative_body": ""
}